jestspectation/__any.py
jestspectation/__assert.py
jestspectation/__config/__config.py
jestspectation/__config/__init__.py
jestspectation/__containers.py
jestspectation/__equals.py
jestspectation/__float_approx.py
jestspectation/__init__.py
jestspectation/__jestspectation_base.py
jestspectation/__py_diffs.py
jestspectation/__strings/__containing.py
jestspectation/__strings/__init__.py
jestspectation/__strings/__lines_like.py
jestspectation/__strings/__matching_regex.py
jestspectation/__strings/__text_like.py
jestspectation/__util.py
jestspectation/logicals/__and.py
jestspectation/logicals/__init__.py
jestspectation/logicals/__not.py
jestspectation/logicals/__or.py
jestspectation/logicals/__xor.py
jestspectation/py.typed
jestspectation/pytest.py
jestspectation-1.4.5.dist-info/LICENSE
jestspectation-1.4.5.dist-info/METADATA
jestspectation-1.4.5.dist-info/WHEEL
jestspectation-1.4.5.dist-info/entry_points.txt
jestspectation-1.4.5.dist-info/RECORD
