Metadata-Version: 2.3
Name: Jestspectation
Version: 1.4.5
Summary: Pattern matching tools to test complex data structures
License: MIT
Keywords: jest,pattern,matching,pytest,equality
Author: Maddy Guthridge
Author-email: hello@maddyguthridge.com
Requires-Python: >=3.9
Classifier: Programming Language :: Python :: 3
Classifier: Intended Audience :: Developers
Classifier: License :: OSI Approved :: MIT License
Classifier: Operating System :: OS Independent
Classifier: Development Status :: 5 - Production/Stable
Classifier: Environment :: Other Environment
Classifier: Framework :: Pytest
Classifier: Topic :: Software Development :: Testing
Classifier: Typing :: Typed
Requires-Dist: typing-extensions (>=4.5.0)
Project-URL: Bug Tracker, https://github.com/MaddyGuthridge/Jestspectation/issues
Project-URL: Documentation, https://maddyguthridge.github.io/Jestspectation
Project-URL: Homepage, https://maddyguthridge.github.io/Jestspectation
Project-URL: Repository, https://github.com/MaddyGuthridge/Jestspectation
